pyNonogram/___init___.py
pyNonogram/errors.py
pyNonogram/nonogram.py
pyNonogram/nonogram_grid.py
pyNonogram-1.0.0.dist-info/LICENSE
pyNonogram-1.0.0.dist-info/METADATA
pyNonogram-1.0.0.dist-info/WHEEL
pyNonogram-1.0.0.dist-info/top_level.txt
pyNonogram-1.0.0.dist-info/RECORD
