Metadata-Version: 2.1
Name: pyNonogram
Version: 1.0.0
Summary: Nonogram framework for Python
Home-page: https://github.com/Apsurt/pyNonogram
Author: Tymon Becella
Author-email: Tymon Becella <tymon@becella.eu>
License: MIT License
Project-URL: Homepage, https://github.com/Apsurt/pyNonogram/
Project-URL: Issues, https://github.com/Apsurt/pyNonogram/issues
Keywords: nonogram,nonograms,griddlers,picross,pic-a-pix,paintbynumbers,puzzle,puzzles
Classifier: Programming Language :: Python :: 3
Classifier: License :: OSI Approved :: MIT License
Classifier: Operating System :: OS Independent
Requires-Python: >=3.8
License-File: LICENSE
Requires-Dist: numpy >=1.19.5
Requires-Dist: pytest >=6.2.4
